django_emailit-0.2.3.dist-info/DESCRIPTION.rst
django_emailit-0.2.3.dist-info/METADATA
django_emailit-0.2.3.dist-info/RECORD
django_emailit-0.2.3.dist-info/WHEEL
django_emailit-0.2.3.dist-info/metadata.json
django_emailit-0.2.3.dist-info/top_level.txt
emailit/__init__.py
emailit/api.py
emailit/models.py
emailit/utils.py
emailit/templates/emailit/base_email.body.html
emailit/templates/emailit/base_email.body.txt
emailit/templates/emailit/email.body.html
emailit/templates/emailit/email.body.txt
emailit/templates/emailit/email.subject.txt
