Metadata-Version: 2.0
Name: django-emailit
Version: 0.2.3
Summary: Make sending html emails easy.
Home-page: http://github.com/divio/django-emailit
Author: Stefan Foulis
Author-email: stefan@foulis.ch
License: BSD
Platform: OS Independent
Classifier: Development Status :: 4 - Beta
Classifier: Framework :: Django
Classifier: Intended Audience :: Developers
Classifier: License :: OSI Approved :: BSD License
Classifier: Operating System :: OS Independent
Classifier: Programming Language :: Python
Classifier: Topic :: Internet :: WWW/HTTP
Requires-Dist: Django (<2.0,>=1.6)
Requires-Dist: premailer (>=1.12)
Requires-Dist: django-absolute
